{
  "_fv": 47,
  "_type": "tool",
  "definition": {
    "toolType": "Sword",
    "renderType": 0,
    "texture": "gramite_dagger",
    "customModelName": "Normal",
    "name": "Gramite Dagger",
    "specialInfo": [],
    "creativeTab": {
      "value": "CUSTOM:TrueDarknessElementariy"
    },
    "harvestLevel": 2,
    "efficiency": 4.0,
    "attackSpeed": 3.0,
    "enchantability": 2,
    "damageVsEntity": 6.0,
    "usageCount": 567,
    "blocksAffected": [],
    "hasGlow": false,
    "repairItems": [
      {
        "value": "CUSTOM:GramiteShard"
      }
    ],
    "immuneToFire": false,
    "stayInGridWhenCrafting": false,
    "damageOnCrafting": false,
    "onItemInInventoryTick": {
      "name": "GramiteDaggerKoghdaInstrumientVInvientarie"
    }
  }
}