{
  "_fv": 47,
  "_type": "tool",
  "definition": {
    "toolType": "Spade",
    "renderType": 0,
    "texture": "soulsteal_shovel",
    "customModelName": "Normal",
    "name": "Soulsteal Shovel",
    "specialInfo": [],
    "creativeTab": {
      "value": "CUSTOM:TrueDarknessElementariy"
    },
    "harvestLevel": 1,
    "efficiency": 4.0,
    "attackSpeed": 2.1,
    "enchantability": 15,
    "damageVsEntity": 4.0,
    "usageCount": 2031,
    "blocksAffected": [],
    "hasGlow": false,
    "repairItems": [
      {
        "value": "CUSTOM:SoulstealIngot"
      }
    ],
    "immuneToFire": false,
    "stayInGridWhenCrafting": false,
    "damageOnCrafting": false
  }
}